[
  {
    "id": 12120,
    "canton": "Vaud",
    "commune": "Aigle",
    "address": "Chemin de Pré d'Emoz 41‑43‑45",
    "type": "Résidentiel",
    "constructionYear": 1990,
    "surface": 2750,
    "vacancy": 0,
    "annualRent": 603960,
    "value": 14850000,
    "grossYield": "4.11 %",
    "netYield": "3.22 %",
    "financing": 5940000,
    "financingPercent": 40,
    "potentialRent": 603960,
    "potentialPercent": 0,
    "construction": "Original",
    "roof": "Tuiles",
    "windows": "PVC double vitrage",
    "heating": "Chauffage central, 2010",
    "facade": "Crépi",
    "notes": "Bien entretenu"
  },
  {
    "id": 12122,
    "canton": "Fribourg",
    "commune": "Fribourg",
    "address": "Rue de la Banque 4",
    "type": "Mixte",
    "constructionYear": 1969,
    "surface": 1546,
    "vacancy": 4.9,
    "annualRent": 367639.2,
    "value": 7928000,
    "grossYield": "4.31 %",
    "netYield": "3.39 %",
    "financing": 3171200,
    "financingPercent": 40,
    "potentialRent": 386500,
    "potentialPercent": 5.1,
    "construction": "Rénovation partielle 2015",
    "roof": "Tuiles",
    "windows": "PVC double vitrage",
    "heating": "Chauffage central, 2015",
    "facade": "Crépi",
    "notes": "Bonne localisation"
  },
  {
    "id": 12123,
    "canton": "Valais",
    "commune": "Martigny",
    "address": "Av. de la Gare 8, 10",
    "type": "Rés.+Comm.",
    "constructionYear": 1961,
    "surface": 4485,
    "vacancy": 5.8,
    "annualRent": 794040,
    "value": 19186000,
    "grossYield": "4.09 %",
    "netYield": "3.05 %",
    "financing": 7674400,
    "financingPercent": 40,
    "potentialRent": 841450,
    "potentialPercent": 6.0,
    "construction": "Rénovation 2010",
    "roof": "Tuiles",
    "windows": "PVC double vitrage",
    "heating": "Chauffage central, 2010",
    "facade": "Pierre",
    "notes": "Excellente localisation"
  },
  {
    "id": 12117,
    "canton": "Valais",
    "commune": "Sion",
    "address": "Av. de la Gare 28",
    "type": "Résidentiel",
    "constructionYear": 1970,
    "surface": 2079,
    "vacancy": 7.4,
    "annualRent": 276873.8,
    "value": 8742000,
    "grossYield": "4.49 %",
    "netYield": "3.65 %",
    "financing": 3496800,
    "financingPercent": 40,
    "potentialRent": 299000,
    "potentialPercent": 8,
    "construction": "Original",
    "roof": "Tuiles",
    "windows": "PVC double vitrage",
    "heating": "Chauffage central, 2000",
    "facade": "Crépi",
    "notes": "Rénovation prévue"
  },
  {
    "id": 12121,
    "canton": "Valais",
    "commune": "Sion",
    "address": "Rue du Scex 2, 4",
    "type": "Rés.+Comm.",
    "constructionYear": 1969,
    "surface": 1820,
    "vacancy": 0,
    "annualRent": 829419,
    "value": 19986000,
    "grossYield": "4.15 %",
    "netYield": "3.27 %",
    "financing": 7994400,
    "financingPercent": 40,
    "potentialRent": 829419,
    "potentialPercent": 0,
    "construction": "Rénovation 2018",
    "roof": "Tuiles",
    "windows": "Aluminium triple vitrage",
    "heating": "Pompe à chaleur, 2018",
    "facade": "Crépi isolant",
    "notes": "Excellent état"
  },
  {
    "id": 13150,
    "canton": "Valais",
    "commune": "Chippis",
    "address": "Grande Avenue 6",
    "type": "Rés.+Comm.",
    "constructionYear": 1925,
    "surface": 698,
    "vacancy": 10,
    "annualRent": 129600,
    "value": 2440000,
    "grossYield": "5.33 %",
    "netYield": "4.00 %",
    "financing": 976000,
    "financingPercent": 40,
    "potentialRent": 144000,
    "potentialPercent": 11.1,
    "construction": "Rénovation partielle 2005",
    "roof": "Tuiles",
    "windows": "Bois double vitrage",
    "heating": "Chauffage central, 2005",
    "facade": "Crépi",
    "notes": "Bâtiment ancien"
  },
  {
    "id": 13136,
    "canton": "Valais",
    "commune": "Martigny",
    "address": "Place Centrale 3",
    "type": "Rés.+Comm.",
    "constructionYear": 1993,
    "surface": 1113,
    "vacancy": 3.5,
    "annualRent": 283447.8,
    "value": 4803000,
    "grossYield": "5.46 %",
    "netYield": "4.12 %",
    "financing": 1921200,
    "financingPercent": 40,
    "potentialRent": 294000,
    "potentialPercent": 3.7,
    "construction": "Original",
    "roof": "Tuiles",
    "windows": "PVC double vitrage",
    "heating": "Chauffage central, 1993",
    "facade": "Crépi",
    "notes": "Bon emplacement commercial"
  },
  {
    "id": 13132,
    "canton": "Valais",
    "commune": "Sion",
    "address": "Av. de Pratifori 5, 7",
    "type": "Rés.+Comm.",
    "constructionYear": 1991,
    "surface": 4062,
    "vacancy": 6.1,
    "annualRent": 809856,
    "value": 17660000,
    "grossYield": "4.69 %",
    "netYield": "3.37 %",
    "financing": 7064000,
    "financingPercent": 40,
    "potentialRent": 861600,
    "potentialPercent": 6.4,
    "construction": "Original",
    "roof": "Tuiles",
    "windows": "PVC double vitrage",
    "heating": "Chauffage central, 1991",
    "facade": "Crépi",
    "notes": "Bonne localisation"
  },
  {
    "id": 13133,
    "canton": "Valais",
    "commune": "Sion",
    "address": "Ch. de St‑Hubert 5",
    "type": "Industriel",
    "constructionYear": 1990,
    "surface": 4179,
    "vacancy": 4.2,
    "annualRent": 606936,
    "value": 8826000,
    "grossYield": "6.63 %",
    "netYield": "5.24 %",
    "financing": 3530400,
    "financingPercent": 40,
    "potentialRent": 633600,
    "potentialPercent": 4.4,
    "construction": "Original",
    "roof": "Métal",
    "windows": "Aluminium double vitrage",
    "heating": "Aérothermes, 1990",
    "facade": "Panneaux sandwich",
    "notes": "Zone industrielle"
  }
]







